arcus/__init__.py
arcus/api_keys.py
arcus/auth.py
arcus/client.py
arcus/exc.py
arcus/version.py
arcus/resources/__init__.py
arcus/resources/accounts.py
arcus/resources/base.py
arcus/resources/bill_payments.py
arcus/resources/billers.py
arcus/resources/bills.py
arcus/resources/transactions.py
tests/__init__.py
tests/conftest.py
tests/test_auth.py
tests/test_client_auth.py
tests/resources/__init__.py
tests/resources/test_accounts.py
tests/resources/test_bill_payments.py
tests/resources/test_billers.py
tests/resources/test_bills.py
tests/resources/test_transactions.py
arcus-1.2.11.dist-info/LICENSE
arcus-1.2.11.dist-info/METADATA
arcus-1.2.11.dist-info/WHEEL
arcus-1.2.11.dist-info/top_level.txt
arcus-1.2.11.dist-info/RECORD
