Metadata-Version: 2.1
Name: arcus
Version: 1.2.11
Summary: Arcus API Client
Home-page: https://github.com/cuenca-mx/arcus-python
Author: Cuenca
Author-email: dev@cuenca.com
Classifier: Programming Language :: Python :: 3
Classifier: Programming Language :: Python :: 3.6
Classifier: Programming Language :: Python :: 3.7
Classifier: License :: OSI Approved :: MIT License
Classifier: Operating System :: OS Independent
Requires-Python: >=3.6
License-File: LICENSE
Requires-Dist: requests (<2.28,>=2.21)
Requires-Dist: pytz (<2021.4,>=2020.1)
Requires-Dist: iso8601 (<1.1,>=0.1)
Requires-Dist: pydash (<5.2,>=4.7)
Requires-Dist: dataclasses (>=0.6) ; python_version < "3.7"
